pust/__init__.py
pust-0.0.0.dist-info/LICENSE.md
pust-0.0.0.dist-info/METADATA
pust-0.0.0.dist-info/WHEEL
pust-0.0.0.dist-info/entry_points.txt
pust-0.0.0.dist-info/pbr.json
pust-0.0.0.dist-info/top_level.txt
pust-0.0.0.dist-info/RECORD
