Metadata-Version: 2.1
Name: pust
Version: 0.0.0
Summary: Use Rust in Python
Home-page: https://github.com/aiwizo/pytorch-datastream
Author: "Jim"
Author-email: jim.holmstroem@gmail.com
License: Apache-2
Project-URL: Source Code, https://github.com/Jim-Holmstroem/pust
Project-URL: Bug Tracker, https://github.com/Jim-Holmstroem/pust/issues
Keywords: rust,performance,high-speed,speed
Platform: Linux
Platform: Darwin
Classifier: Development Status :: 3 - Alpha
Classifier: Environment :: Other Environment
Classifier: License :: OSI Approved :: Apache Software License
Classifier: Operating System :: OS Independent
Classifier: Programming Language :: Python :: 3
Classifier: Programming Language :: Python :: 3.6
Classifier: Programming Language :: Python :: 3.7
Classifier: Programming Language :: Python :: 3.8
Classifier: Intended Audience :: Developers
Classifier: Intended Audience :: Science/Research
Classifier: Topic :: Scientific/Engineering
Classifier: Topic :: Software Development
Classifier: Topic :: Software Development :: Libraries
Classifier: Topic :: Software Development :: Libraries :: Python Modules
Requires-Python: >=3.6
